sqlalchemy_helpers/__init__.py
sqlalchemy_helpers/aio.py
sqlalchemy_helpers/fastapi.py
sqlalchemy_helpers/flask_ext.py
sqlalchemy_helpers/manager.py
sqlalchemy_helpers/py.typed
sqlalchemy_helpers-2.0.1.dist-info/LICENSES/LGPL-3.0-or-later.txt
sqlalchemy_helpers-2.0.1.dist-info/METADATA
sqlalchemy_helpers-2.0.1.dist-info/WHEEL
sqlalchemy_helpers-2.0.1.dist-info/RECORD
