Metadata-Version: 2.3
Name: sqlalchemy-helpers
Version: 2.0.1
Summary: SQLAlchemy Helpers
License: LGPL-3.0-or-later
Keywords: database,web,fedora
Author: Fedora Infrastructure
Author-email: admin@fedoraproject.org
Requires-Python: >=3.10.0,<4.0.0
Classifier: Development Status :: 5 - Production/Stable
Classifier: Environment :: Web Environment
Classifier: License :: OSI Approved :: GNU Lesser General Public License v3 or later (LGPLv3+)
Classifier: Programming Language :: Python :: 3
Classifier: Programming Language :: Python :: 3.10
Classifier: Programming Language :: Python :: 3.11
Classifier: Programming Language :: Python :: 3.12
Classifier: Programming Language :: Python :: 3.13
Classifier: Topic :: Database
Classifier: Topic :: Internet :: WWW/HTTP :: Dynamic Content
Provides-Extra: docs
Provides-Extra: fastapi
Provides-Extra: flask
Requires-Dist: Flask (>=2.0.0,<4.0.0) ; extra == "flask" or extra == "docs"
Requires-Dist: SQLAlchemy[asyncio] (>=2.0.0)
Requires-Dist: alembic (>=1.6.5)
Requires-Dist: fastapi (>=0.100.0) ; extra == "fastapi"
Requires-Dist: myst-parser ; extra == "docs"
Requires-Dist: pydantic (>=2.0) ; extra == "fastapi"
Requires-Dist: sphinx ; extra == "docs"
Requires-Dist: sphinxcontrib-napoleon ; extra == "docs"
Project-URL: Homepage, http://github.com/fedora-infra/sqlalchemy-helpers
Project-URL: Repository, http://github.com/fedora-infra/sqlalchemy-helpers
